autopilot_tools/01_print_info.py
autopilot_tools/02_print_more.py
autopilot_tools/03_input.py
autopilot_tools/04_format.py
autopilot_tools/05_func.py
autopilot_tools/06_object.py
autopilot_tools/07_file.py
autopilot_tools/08_write.py
autopilot_tools/09_try_except_final.py
autopilot_tools/10_decorator.py
autopilot_tools/11_yield.py
autopilot_tools/12_asyncio.py
autopilot_tools/__init__.py
autopilot_tools/calculator.py
autopilot_tools/test_calculator.py
lin_autopilot_tools-0.1.0.dist-info/METADATA
lin_autopilot_tools-0.1.0.dist-info/WHEEL
lin_autopilot_tools-0.1.0.dist-info/top_level.txt
lin_autopilot_tools-0.1.0.dist-info/RECORD
